{
  "schemaVersion": 1,
  "packages": [
    {
      "id": "marked",
      "name": "marked",
      "version": "12.0.2",
      "purpose": "Parses Markdown chapter text into HTML before sanitizing and rendering.",
      "license": "MIT",
      "licenseUrl": "https://github.com/markedjs/marked/blob/master/LICENSE.md",
      "website": "https://marked.js.org/"
    },
    {
      "id": "dompurify",
      "name": "DOMPurify",
      "version": "3.1.6",
      "purpose": "Sanitizes generated HTML so user-authored Markdown content is safe to inject.",
      "license": "Apache-2.0",
      "licenseUrl": "https://github.com/cure53/DOMPurify/blob/main/LICENSE",
      "website": "https://github.com/cure53/DOMPurify"
    },
    {
      "id": "qrcodejs",
      "name": "qrcodejs",
      "version": "1.0.0",
      "purpose": "Generates QR codes for URL/asset references in page rendering and exports.",
      "license": "MIT",
      "licenseUrl": "https://github.com/davidshimjs/qrcodejs/blob/master/LICENSE",
      "website": "https://github.com/davidshimjs/qrcodejs"
    },
    {
      "id": "html2canvas",
      "name": "html2canvas",
      "version": "1.4.1",
      "purpose": "Captures rendered DOM pages into bitmap canvases for PDF/image/video export pipelines.",
      "license": "MIT",
      "licenseUrl": "https://github.com/niklasvh/html2canvas/blob/master/LICENSE",
      "website": "https://html2canvas.hertzen.com/"
    },
    {
      "id": "jspdf",
      "name": "jsPDF",
      "version": "2.5.1",
      "purpose": "Builds interior, cover, and eBook PDF documents from rendered page canvases.",
      "license": "MIT",
      "licenseUrl": "https://github.com/parallax/jsPDF/blob/master/LICENSE",
      "website": "https://github.com/parallax/jsPDF"
    },
    {
      "id": "jszip",
      "name": "JSZip",
      "version": "3.10.1",
      "purpose": "Bundles exported page images into downloadable ZIP archives.",
      "license": "MIT",
      "licenseUrl": "https://github.com/Stuk/jszip/blob/main/LICENSE.markdown",
      "website": "https://stuk.github.io/jszip/"
    },
    {
      "id": "gifenc",
      "name": "gifenc",
      "version": "latest (unpkg CDN)",
      "purpose": "Encodes GIF frames for preview and animated GIF export.",
      "license": "MIT",
      "licenseUrl": "https://github.com/mattdesl/gifenc/blob/master/LICENSE.md",
      "website": "https://github.com/mattdesl/gifenc"
    },
    {
      "id": "mp4-muxer",
      "name": "mp4-muxer",
      "version": "latest (unpkg CDN)",
      "purpose": "Muxes encoded video chunks into an MP4 container for export.",
      "license": "MIT",
      "licenseUrl": "https://github.com/Vanilagy/mp4-muxer/blob/main/LICENSE",
      "website": "https://github.com/Vanilagy/mp4-muxer"
    }
  ]
}
